django_sa/__init__.py
django_sa/sa.py
django_sa/utils.py
django_sa-0.1.dist-info/DESCRIPTION.rst
django_sa-0.1.dist-info/METADATA
django_sa-0.1.dist-info/RECORD
django_sa-0.1.dist-info/WHEEL
django_sa-0.1.dist-info/metadata.json
django_sa-0.1.dist-info/top_level.txt
