Metadata-Version: 2.0
Name: django-sa
Version: 0.1
Summary: Utility to convert a python script into a standalone django script
Home-page: https://github.com/kasun/django-sa
Author: Kasun Herath
Author-email: kasunh01@gmail.com
License: MIT
Keywords: django_sa,Django standalone
Platform: UNKNOWN
Classifier: Development Status :: 3 - Alpha
Classifier: Framework :: Django
Classifier: Framework :: Django :: 1.7
Classifier: Framework :: Django :: 1.8
Classifier: Framework :: Django :: 1.9
Classifier: Framework :: Django :: 1.10
Classifier: Framework :: Django :: 1.11
Classifier: Intended Audience :: Developers
Classifier: License :: OSI Approved :: MIT License
Classifier: Natural Language :: English
Classifier: Programming Language :: Python :: 2
Classifier: Programming Language :: Python :: 3
